Metadata-Version: 2.1
Name: porter-schmorter
Version: 0.16.8
Summary: porter is a framework for exposing machine learning models via REST APIs.
Author-email: Dante Gates <dantedgates@gmail.com>
Project-URL: Homepage, https://github.com/dantegates/porter
Project-URL: Bug Tracker, https://github.com/dantegates/porter/issues
Classifier: Programming Language :: Python :: 3
Classifier: Programming Language :: Python :: 3.9
Classifier: Programming Language :: Python :: 3.10
Classifier: Programming Language :: Python :: 3.11
Classifier: License :: OSI Approved :: MIT License
Classifier: Operating System :: OS Independent
Requires-Python: >=3.9
License-File: LICENSE
Requires-Dist: Flask <4.0.0,>=3.0.0
Requires-Dist: numpy >=1.24.0
Requires-Dist: pandas >=2.0.0
Requires-Dist: joblib >=1.3.0
Requires-Dist: fastjsonschema >=2.18.0
Provides-Extra: all
Requires-Dist: porter-schmorter[dev,keras-utils,sklearn-utils] ; extra == 'all'
Provides-Extra: dev
Requires-Dist: pytest ; extra == 'dev'
Requires-Dist: sphinx ; extra == 'dev'
Requires-Dist: sphinx-rtd-theme ; extra == 'dev'
Requires-Dist: tensorflow >=2.16 ; extra == 'dev'
Provides-Extra: keras-utils
Requires-Dist: keras >=3.0 ; extra == 'keras-utils'
Provides-Extra: sklearn-utils
Requires-Dist: scikit-learn >=1.3.0 ; extra == 'sklearn-utils'
